amazon_web_services_helpers/__init__.py
amazon_web_services_helpers/aws_helper.py
amazon_web_services_helpers/document_store.py
amazon_web_services_helpers/dynamo_db_helper.py
amazon_web_services_helpers/file_helper.py
amazon_web_services_helpers/s3_helper.py
amazon_web_services_helpers-1.0.8.dist-info/METADATA
amazon_web_services_helpers-1.0.8.dist-info/WHEEL
amazon_web_services_helpers-1.0.8.dist-info/namespace_packages.txt
amazon_web_services_helpers-1.0.8.dist-info/top_level.txt
amazon_web_services_helpers-1.0.8.dist-info/zip-safe
amazon_web_services_helpers-1.0.8.dist-info/RECORD
