Metadata-Version: 2.1
Name: amazon-web-services-helpers
Version: 1.0.8
Summary: UNKNOWN
Home-page: UNKNOWN
Author: 
Author-email: 
Maintainer: 
Maintainer-email: 
License: UNKNOWN
Platform: UNKNOWN
Classifier: Development Status :: 3 - Alpha
Classifier: Programming Language :: Python
Requires-Dist: boto3
